pip_terraform-0.2.1.dist-info/licenses/LICENSE
terraform_install/__init__.py
terraform_install/cli.py
pip_terraform-0.2.1.dist-info/METADATA
pip_terraform-0.2.1.dist-info/WHEEL
pip_terraform-0.2.1.dist-info/entry_points.txt
pip_terraform-0.2.1.dist-info/top_level.txt
pip_terraform-0.2.1.dist-info/RECORD
